{
    "name": "Yu-Gi-Oh!",
    "formats": "",
    "trimmed": "y",
    "image_type": "jpg",
    "draft_structure": "play booster",
    "cards": [
        {
            "card_name": "CW03 Familiar Knight",
            "color": "W",
            "rarity": "common",
            "type": "Creature \u2014 Knight",
            "number": 20,
            "color_identity": "W",
            "cost": "{1}{W}",
            "rules_text": "When this creature dies, create a 2/1 white Soldier creature token with \u201cThis creature cannot block.\u201d",
            "flavor_text": "[i][/i]",
            "pt": "2/1",
            "special_text": "",
            "shape": "normal",
            "set": "YGO",
            "loyalty": "",
            "artist": "ygoFamiliar Knight",
            "notes": "!related Soldier"
        },
        {
            "card_name": "CW06 Spear Dragon",
            "color": "W",
            "rarity": "common",
            "type": "Creature \u2014 Dragon",
            "number": 23,
            "color_identity": "W",
            "cost": "{2}{W}",
            "rules_text": "Flying\nWhen this creature attacks, put a +1/+1 counter on another target creature you control.",
            "flavor_text": "[i][/i]",
            "pt": "1/3",
            "special_text": "",
            "shape": "normal",
            "set": "YGO",
            "loyalty": "",
            "artist": "ygoSpear Dragon",
            "notes": ""
        },
        {
            "card_name": "CW11 Celtic Guardian",
            "color": "W",
            "rarity": "common",
            "type": "Creature \u2014 Elf Soldier",
            "number": 28,
            "color_identity": "W",
            "cost": "{3}{W}",
            "rules_text": "Vigilance [i](Attacking doesn't cause this creature to tap.)[/i]\n[i][i]Home Plains \u2014[/i][/i] this creature has first strike as long as you control three or more Plains.",
            "flavor_text": "[i][/i]",
            "pt": "4/3",
            "special_text": "",
            "shape": "normal",
            "set": "YGO",
            "loyalty": "",
            "artist": "ygoCeltic Guardian",
            "notes": ""
        },
        {
            "card_name": "CW09 Breaker, the Magical Warrior",
            "color": "W",
            "rarity": "common",
            "type": "Legendary Creature \u2014 Elf Warrior",
            "number": 26,
            "color_identity": "W",
            "cost": "{2}{W}{W}",
            "rules_text": "When this creature enters, place a +1/+1 counter on it.\n{2}{W}, remove a +1/+1 counter from this creature: Destroy target enchantment. Activate only as a sorcery.",
            "flavor_text": "[i][/i]",
            "pt": "2/3",
            "special_text": "",
            "shape": "normal",
            "set": "YGO",
            "loyalty": "",
            "artist": "ygoBreaker the Magical Warrior",
            "notes": ""
        },
        {
            "card_name": "CW05 Beaver Warrior",
            "color": "W",
            "rarity": "common",
            "type": "Creature \u2014 Beaver Warrior",
            "number": 22,
            "color_identity": "W",
            "cost": "{2}{W}",
            "rules_text": "Vigilance\n[i][i]Home Plains \u2014[/i][/i] While you control three or more Plains, this creature has ward {3} [i](Whenever this creature becomes the target of a spell or ability an opponent controls, counter it unless that player pays {3}.)[/i]",
            "flavor_text": "[i][/i]",
            "pt": "2/3",
            "special_text": "",
            "shape": "normal",
            "set": "YGO",
            "loyalty": "",
            "artist": "ygoBeaver Warrior",
            "notes": ""
        },
        {
            "card_name": "CW08 Mystical Elf",
            "color": "W",
            "rarity": "common",
            "type": "Creature \u2014 Elf Cleric",
            "number": 25,
            "color_identity": "W",
            "cost": "{3}{W}",
            "rules_text": "When this creature enters, target creature you control gets +1/+1 until end of turn.\nForetell {1}{W} [i](During your turn, you may pay {2} and exile this card from your hand face down. Cast it on a later turn for its foretell cost.)[/i]",
            "flavor_text": "[i][/i]",
            "pt": "2/4",
            "special_text": "",
            "shape": "normal",
            "set": "YGO",
            "loyalty": "",
            "artist": "ygoMystical Elf",
            "notes": ""
        },
        {
            "card_name": "CW04 Holding Arms",
            "color": "W",
            "rarity": "common",
            "type": "Artifact Creature \u2014 Construct",
            "number": 21,
            "color_identity": "W",
            "cost": "{1}{W}",
            "rules_text": "When this creature enters, exile target creature an opponent controls until this creature leaves the battlefield.",
            "flavor_text": "[i][/i]",
            "pt": "0/2",
            "special_text": "",
            "shape": "normal",
            "set": "YGO",
            "loyalty": "",
            "artist": "ygoHolding Arms",
            "notes": ""
        },
        {
            "card_name": "CW10 Hyozanryu",
            "color": "W",
            "rarity": "common",
            "type": "Creature \u2014 Dragon",
            "number": 27,
            "color_identity": "W",
            "cost": "{4}{W}",
            "rules_text": "Tribute summon {3} [i](Each untapped creature with power 2 or more you sacrifice while casting this spell pays for {3}.)[/i]\nFlying",
            "flavor_text": "[i][/i]",
            "pt": "3/4",
            "special_text": "",
            "shape": "normal",
            "set": "YGO",
            "loyalty": "",
            "artist": "ygoHyozanryu",
            "notes": ""
        },
        {
            "card_name": "CW07 Stray Lambs",
            "color": "W",
            "rarity": "common",
            "type": "Sorcery",
            "number": 24,
            "color_identity": "W",
            "cost": "{2}{W}",
            "rules_text": "Create two 1/1 white Goat creature tokens.\nForetell {W} [i](During your turn, you may pay {2} and exile this card from your hand face down. Cast it on a later turn for its foretell cost.)[/i]",
            "flavor_text": "[i][/i]",
            "pt": "",
            "special_text": "",
            "shape": "normal",
            "set": "YGO",
            "loyalty": "",
            "artist": "ygoStray Lambs",
            "notes": "!related Goat"
        },
        {
            "card_name": "CW13 Waboku",
            "color": "W",
            "rarity": "common",
            "type": "Instant",
            "number": 30,
            "color_identity": "W",
            "cost": "{2}{W}",
            "rules_text": "Target creature gets +2/+2 and gains indestructible until end of turn. \nScry 2",
            "flavor_text": "[i][/i]",
            "pt": "",
            "special_text": "",
            "shape": "normal",
            "set": "YGO",
            "loyalty": "",
            "artist": "ygoWaboku",
            "notes": ""
        },
        {
            "card_name": "CW14 Reinforcement of the Army",
            "color": "W",
            "rarity": "common",
            "type": "Instant",
            "number": 31,
            "color_identity": "W",
            "cost": "{3}{W}",
            "rules_text": "Creatures you control get +2/+1 until end of turn.\nForetell {1}{W} [i](During your turn, you may pay {2} and exile this card from your hand face down. Cast it on a later turn for its foretell cost.)[/i]",
            "flavor_text": "[i][/i]",
            "pt": "",
            "special_text": "",
            "shape": "normal",
            "set": "YGO",
            "loyalty": "",
            "artist": "ygoReinforcement of the Army",
            "notes": ""
        },
        {
            "card_name": "CW12 Light of Intervention",
            "color": "W",
            "rarity": "common",
            "type": "Instant",
            "number": 29,
            "color_identity": "W",
            "cost": "{1}{W}",
            "rules_text": "This spell deals 4 damage to target attacking or blocking creature.",
            "flavor_text": "[i][/i]",
            "pt": "",
            "special_text": "",
            "shape": "normal",
            "set": "YGO",
            "loyalty": "",
            "artist": "ygoLight of Intervention",
            "notes": ""
        },
        {
            "card_name": "CW15 United We Stand",
            "color": "W",
            "rarity": "common",
            "type": "Enchantment \u2014 Aura",
            "number": 32,
            "color_identity": "W",
            "cost": "{3}{W}",
            "rules_text": "Enchant creature.\nEnchanted creature gets +X/+X, where X is the number of creatures you control.",
            "flavor_text": "[i][/i]",
            "pt": "",
            "special_text": "",
            "shape": "normal",
            "set": "YGO",
            "loyalty": "",
            "artist": "ygoUnited We Stand",
            "notes": ""
        },
        {
            "card_name": "CU01 Stealth Bird",
            "color": "U",
            "rarity": "common",
            "type": "Creature \u2014 Bird",
            "number": 56,
            "color_identity": "U",
            "cost": "{U}",
            "rules_text": "Flying [i](This creature can't be blocked except by creatures with flying or reach.)[/i]\n{2}{U}: Draw a card, then discard a card.",
            "flavor_text": "[i][/i]",
            "pt": "1/2",
            "special_text": "",
            "shape": "normal",
            "set": "YGO",
            "loyalty": "",
            "artist": "ygoStealth Bird",
            "notes": ""
        },
        {
            "card_name": "CU03 Illusionist Faceless Mage",
            "color": "U",
            "rarity": "common",
            "type": "Creature \u2014 Illusion Wizard",
            "number": 58,
            "color_identity": "U",
            "cost": "{2}{U}",
            "rules_text": "Ward {2} [i](Whenever this creature becomes the target of a spell or ability an opponent controls, counter it unless that player pays {2}.)[/i]\nWhen this creature enters, scry 2.",
            "flavor_text": "[i][/i]",
            "pt": "2/2",
            "special_text": "",
            "shape": "normal",
            "set": "YGO",
            "loyalty": "",
            "artist": "ygoIllusionist Faceless mage",
            "notes": ""
        },
        {
            "card_name": "CU02 Element Magician",
            "color": "U",
            "rarity": "common",
            "type": "Creature \u2014 Human Wizard",
            "number": 57,
            "color_identity": "U",
            "cost": "{1}{U}",
            "rules_text": "Prowess [i](Whenever you cast a noncreature spell, this creature gets +1/+1 until end of turn.)[/i]\nThis creature enters tapped.",
            "flavor_text": "[i][/i]",
            "pt": "2/2",
            "special_text": "",
            "shape": "normal",
            "set": "YGO",
            "loyalty": "",
            "artist": "ygoElement Magician",
            "notes": "!tapped"
        },
        {
            "card_name": "CU04 Toon Mermaid",
            "color": "U",
            "rarity": "common",
            "type": "Creature \u2014 Merfolk Archer",
            "number": 59,
            "color_identity": "U",
            "cost": "{2}{U}",
            "rules_text": "This creature enters with an additional +1/+1 counter if it was foretold.\nForetell {1}{U} [i](During your turn, you may pay {2} and exile this card from your hand face down. Cast it on a later turn for its foretell cost.)[/i]",
            "flavor_text": "[i][/i]",
            "pt": "2/3",
            "special_text": "",
            "shape": "normal",
            "set": "YGO",
            "loyalty": "",
            "artist": "ygoToon Mermaid",
            "notes": ""
        },
        {
            "card_name": "CU08 Kairyu-shin",
            "color": "U",
            "rarity": "common",
            "type": "Creature \u2014 Serpent",
            "number": 63,
            "color_identity": "U",
            "cost": "{6}{U}",
            "rules_text": "[i][i]Home Island [/i]\u2014[/i] This creature has trample as long as you control three or more Islands.",
            "flavor_text": "[i][/i]",
            "pt": "7/7",
            "special_text": "",
            "shape": "normal",
            "set": "YGO",
            "loyalty": "",
            "artist": "ygoKairyu-shin",
            "notes": ""
        },
        {
            "card_name": "CU09 Compulsory Evactuation Device",
            "color": "U",
            "rarity": "common",
            "type": "Instant",
            "number": 64,
            "color_identity": "U",
            "cost": "{U}",
            "rules_text": "Choose one \u2014\n\u2022 Counter target creature spell unless its controller pays {1}.\n\u2022 Return target creature to its owner's hand.",
            "flavor_text": "[i][/i]",
            "pt": "",
            "special_text": "",
            "shape": "normal",
            "set": "YGO",
            "loyalty": "",
            "artist": "ygoCompulsory Evacuation Device",
            "notes": ""
        },
        {
            "card_name": "CU10 Mask of Dispel",
            "color": "U",
            "rarity": "common",
            "type": "Enchantment \u2014 Aura",
            "number": 65,
            "color_identity": "U",
            "cost": "{1}{U}",
            "rules_text": "Flash [i](You may cast this spell any time you could cast an instant.)[/i]\nEnchant creature\nEnchanted creature loses all abilities and is a black Imp with base power and toughness 1/1.",
            "flavor_text": "[i][/i]",
            "pt": "",
            "special_text": "",
            "shape": "normal",
            "set": "YGO",
            "loyalty": "",
            "artist": "ygoMask of Dispel",
            "notes": ""
        },
        {
            "card_name": "CU11 Spellbinding Circle",
            "color": "U",
            "rarity": "common",
            "type": "Sorcery",
            "number": 66,
            "color_identity": "U",
            "cost": "{2}{U}",
            "rules_text": "Tap target creature and put three stun counters on it. [i](If a permanent with a stun counter would become untapped, remove one from it instead.)[/i]\nForetell {U} [i](During your turn, you may pay {2} and exile this card from your hand face down. Cast it on a later turn for its foretell cost.)[/i]",
            "flavor_text": "[i][/i]",
            "pt": "",
            "special_text": "",
            "shape": "normal",
            "set": "YGO",
            "loyalty": "",
            "artist": "ygoSpellbinding Circle",
            "notes": ""
        },
        {
            "card_name": "CU12 Pot of Greed",
            "color": "U",
            "rarity": "common",
            "type": "Artifact",
            "number": 67,
            "color_identity": "U",
            "cost": "{2}{U}",
            "rules_text": "This artifact enters with two greed counters on it.\n{T}: Put a greed counter on this artifact.\n{2}{U}, {T}, Sacrifice this artifact: Draw cards equal to the number of greed counters on this artifact.",
            "flavor_text": "[i][/i]",
            "pt": "",
            "special_text": "",
            "shape": "normal",
            "set": "YGO",
            "loyalty": "",
            "artist": "ygoPot of Greed",
            "notes": ""
        },
        {
            "card_name": "CU13 De-Spell",
            "color": "U",
            "rarity": "common",
            "type": "Instant",
            "number": 68,
            "color_identity": "U",
            "cost": "{1}{U}{U}",
            "rules_text": "Counter target spell.\nScry 2.",
            "flavor_text": "[i][/i]",
            "pt": "",
            "special_text": "",
            "shape": "normal",
            "set": "YGO",
            "loyalty": "",
            "artist": "ygoDe-Spell",
            "notes": ""
        },
        {
            "card_name": "CU14 Mist Body",
            "color": "U",
            "rarity": "common",
            "type": "Enchantment",
            "number": 69,
            "color_identity": "U",
            "cost": "{3}{U}",
            "rules_text": "Enchant creature\nWhen this enchantment enters, draw two cards.\nEnchanted creature has flying.\nForetell {1}{U} [i](During your turn, you may pay {2} and exile this card from your hand face down. Cast it on a later turn for its foretell cost.)[/i]",
            "flavor_text": "[i][/i]",
            "pt": "",
            "special_text": "",
            "shape": "normal",
            "set": "YGO",
            "loyalty": "",
            "artist": "ygoMist Body",
            "notes": ""
        },
        {
            "card_name": "CU15 Magic Drain",
            "color": "U",
            "rarity": "common",
            "type": "Instant",
            "number": 70,
            "color_identity": "U",
            "cost": "{3}{U}{U}",
            "rules_text": "Counter target spell. Scry X, then draw a card, where X is that spell's mana value.\nForetell {1}{U}{U} [i](During your turn, you may pay {2} and exile this card from your hand face down. Cast it on a later turn for its foretell cost.)[/i]",
            "flavor_text": "[i][/i]",
            "pt": "",
            "special_text": "",
            "shape": "normal",
            "set": "YGO",
            "loyalty": "",
            "artist": "ygoMagic Drain",
            "notes": ""
        },
        {
            "card_name": "CB01 Kuriboh",
            "color": "B",
            "rarity": "common",
            "type": "Creature \u2014 Imp",
            "number": 94,
            "color_identity": "B",
            "cost": "{B}",
            "rules_text": "{2}{B}{B}: Search your library for any number of cards named Kuriboh, reveal them, put them into your hand, then shuffle.\nA deck can have any number of cards named Kuriboh.",
            "flavor_text": "[i][/i]",
            "pt": "1/1",
            "special_text": "",
            "shape": "normal",
            "set": "YGO",
            "loyalty": "",
            "artist": "ygoKuriboh",
            "notes": ""
        },
        {
            "card_name": "CB02 Night Assailant",
            "color": "B",
            "rarity": "common",
            "type": "Creature \u2014 Shade Assassin",
            "number": 95,
            "color_identity": "B",
            "cost": "{1}{B}",
            "rules_text": "During your turn this creature has lifelink.\n{2}{B}: This creature gets +1/+1 until end of turn.",
            "flavor_text": "[i][/i]",
            "pt": "1/1",
            "special_text": "",
            "shape": "normal",
            "set": "YGO",
            "loyalty": "",
            "artist": "ygoNight Assailant",
            "notes": ""
        },
        {
            "card_name": "CB03 Double Coston",
            "color": "B",
            "rarity": "common",
            "type": "Creature \u2014 Spirit",
            "number": 96,
            "color_identity": "B",
            "cost": "{1}{B}",
            "rules_text": "When this creature dies, create a 1/1 black Spirit creature token.",
            "flavor_text": "[i][/i]",
            "pt": "2/1",
            "special_text": "",
            "shape": "normal",
            "set": "YGO",
            "loyalty": "",
            "artist": "ygoDouble Coston",
            "notes": "!related Spirit"
        },
        {
            "card_name": "CB04 Steel Scorpion",
            "color": "B",
            "rarity": "common",
            "type": "Artifact Creature \u2014 Scorpion",
            "number": 97,
            "color_identity": "B",
            "cost": "{2}{B}",
            "rules_text": "When this creature enters, each opponent discards a card.",
            "flavor_text": "[i][/i]",
            "pt": "2/2",
            "special_text": "",
            "shape": "normal",
            "set": "YGO",
            "loyalty": "",
            "artist": "ygoSteel Scorpion",
            "notes": ""
        },
        {
            "card_name": "CB06 Mammoth Graveyard",
            "color": "B",
            "rarity": "common",
            "type": "Creature \u2014 Elephant Skeleton",
            "number": 99,
            "color_identity": "B",
            "cost": "{3}{B}",
            "rules_text": "Menace\n{2}{B}: Return this card from your graveyard to your hand.",
            "flavor_text": "[i][/i]",
            "pt": "3/2",
            "special_text": "",
            "shape": "normal",
            "set": "YGO",
            "loyalty": "",
            "artist": "ygoMammoth Graveyard",
            "notes": ""
        },
        {
            "card_name": "CB05 Flash Assailant",
            "color": "B",
            "rarity": "common",
            "type": "Creature \u2014 Human Assassin",
            "number": 98,
            "color_identity": "B",
            "cost": "{2}{B}",
            "rules_text": "This creature gets -X/-X, where X is the number of cards in your hand.",
            "flavor_text": "[i][/i]",
            "pt": "5/5",
            "special_text": "",
            "shape": "normal",
            "set": "YGO",
            "loyalty": "",
            "artist": "ygoFlash Assasilant",
            "notes": ""
        },
        {
            "card_name": "CB07 Berfomet",
            "color": "B",
            "rarity": "common",
            "type": "Legendary Creature \u2014 Demon",
            "number": 100,
            "color_identity": "B",
            "cost": "{2}{B}{B}{B}",
            "rules_text": "Tribute summon {2} [i](Each untapped creature with power 2 or more you sacrifice while casting this spell pays for {2}.)[/i]\nFlying\nWhen this creature enters, target opponent loses 2 life and you gain 2 life.",
            "flavor_text": "[i][/i]",
            "pt": "4/3",
            "special_text": "",
            "shape": "normal",
            "set": "YGO",
            "loyalty": "",
            "artist": "ygoBerfomet",
            "notes": ""
        },
        {
            "card_name": "CB08 Shadow Ghoul",
            "color": "B",
            "rarity": "common",
            "type": "Creature \u2014 Horror",
            "number": 101,
            "color_identity": "B",
            "cost": "{3}{B}",
            "rules_text": "Whenever another creature you control dies, put a +1/+1 counter on this creature.\nForetell {1}{B} [i](During your turn, you may pay {2} and exile this card from your hand face down. Cast it on a later turn for its foretell cost.)[/i]",
            "flavor_text": "[i][/i]",
            "pt": "3/3",
            "special_text": "",
            "shape": "normal",
            "set": "YGO",
            "loyalty": "",
            "artist": "ygoShadow Ghoul",
            "notes": ""
        },
        {
            "card_name": "CB09 Beast of Talwar",
            "color": "B",
            "rarity": "common",
            "type": "Creature \u2014 Demon",
            "number": 102,
            "color_identity": "B",
            "cost": "{6}{B}",
            "rules_text": "Tribute Summon {3} [i](Each untapped creature with power 2 or more you sacrifice while casting this spell pays for {3}.)[/i]\nFlying, trample",
            "flavor_text": "[i][/i]",
            "pt": "5/5",
            "special_text": "",
            "shape": "normal",
            "set": "YGO",
            "loyalty": "",
            "artist": "ygoBeast of Talwar",
            "notes": ""
        },
        {
            "card_name": "CB10 Trap Hole",
            "color": "B",
            "rarity": "common",
            "type": "Instant",
            "number": 103,
            "color_identity": "B",
            "cost": "{B}",
            "rules_text": "As an additional cost to cast this spell, take a risk. [i](Discard a card, then look at the top card of your library. If it shares a card type with the discarded card, you may reveal it and put it into your hand.)[/i]\nDestroy target creature. You lose life equal to that creature's mana value.",
            "flavor_text": "[i][/i]",
            "pt": "",
            "special_text": "",
            "shape": "normal",
            "set": "YGO",
            "loyalty": "",
            "artist": "ygoTrap Hole",
            "notes": ""
        },
        {
            "card_name": "CB11 Kunai with Chain",
            "color": "B",
            "rarity": "common",
            "type": "Artifact \u2014 Equipment",
            "number": 104,
            "color_identity": "B",
            "cost": "{1}{B}",
            "rules_text": "Flash\nWhen this artifact enters, attach it to target creature you control. That creature gains deathtouch until end of turn.\nEquipped creature gets +2/+0.\nEquip {1} [i]({1}: Attach to target creature you control. Equip only as a sorcery.)[/i]",
            "flavor_text": "[i][/i]",
            "pt": "",
            "special_text": "",
            "shape": "normal",
            "set": "YGO",
            "loyalty": "",
            "artist": "ygoKunai with Chain",
            "notes": ""
        },
        {
            "card_name": "CB12 Reckless Greed",
            "color": "B",
            "rarity": "common",
            "type": "Sorcery",
            "number": 105,
            "color_identity": "B",
            "cost": "{1}{B}",
            "rules_text": "Draw two cards, then take a risk. If you didn't reveal a card this way, lose 3 life. [i](To take a risk, discard a card, then look at the top card of your library. If it shares a card type with the discarded card, you may reveal it and put it into your hand.)[/i]",
            "flavor_text": "[i][/i]",
            "pt": "",
            "special_text": "",
            "shape": "normal",
            "set": "YGO",
            "loyalty": "",
            "artist": "ygoReckless Greed",
            "notes": ""
        },
        {
            "card_name": "CB13 Mind Crush",
            "color": "B",
            "rarity": "common",
            "type": "Sorcery",
            "number": 106,
            "color_identity": "B",
            "cost": "{2}{B}",
            "rules_text": "Target opponent reveals their hand. You choose a nonland card from it. That player discards it.\nForetell {B} [i](During your turn, you may pay {2} and exile this card from your hand face down. Cast it on a later turn for its foretell cost.)[/i]",
            "flavor_text": "[i][/i]",
            "pt": "",
            "special_text": "",
            "shape": "normal",
            "set": "YGO",
            "loyalty": "",
            "artist": "ygoMind Crush",
            "notes": ""
        },
        {
            "card_name": "CB14 Tribute to the Doomed",
            "color": "B",
            "rarity": "common",
            "type": "Instant",
            "number": 107,
            "color_identity": "B",
            "cost": "{1}{B}{B}",
            "rules_text": "Destroy target creature or planeswalker. Surveil 1. [i](Look at the top card of your library. You may put it into your graveyard.)[/i]",
            "flavor_text": "[i][/i]",
            "pt": "",
            "special_text": "",
            "shape": "normal",
            "set": "YGO",
            "loyalty": "",
            "artist": "ygoTribute to the Doomed",
            "notes": ""
        },
        {
            "card_name": "CB15 Soul Taker",
            "color": "B",
            "rarity": "common",
            "type": "Sorcery",
            "number": 108,
            "color_identity": "B",
            "cost": "{3}{B}{B}",
            "rules_text": "As you cast this spell, you may take a risk. [i](Discard a card, then look at the top card of your library. If it shares a card type with the discarded card, you may reveal it and put it into your hand.)[/i]\nDestroy target creature. Then if you took the risk, Its controller loses X life and you gain X life, where X is that creature's power.",
            "flavor_text": "[i][/i]",
            "pt": "",
            "special_text": "",
            "shape": "normal",
            "set": "YGO",
            "loyalty": "",
            "artist": "ygoSoul Taker",
            "notes": ""
        },
        {
            "card_name": "CR01 Hinotama Soul",
            "color": "R",
            "rarity": "common",
            "type": "Creature \u2014 Elemental",
            "number": 132,
            "color_identity": "R",
            "cost": "{R}",
            "rules_text": "[i][i]Home Mountain \u2014[/i][/i] As long as you control three or more Mountains, this creature gets +2/+0 and gains trample.",
            "flavor_text": "[i][/i]",
            "pt": "1/1",
            "special_text": "",
            "shape": "normal",
            "set": "YGO",
            "loyalty": "",
            "artist": "ygoHinotama Soul",
            "notes": ""
        },
        {
            "card_name": "CR02 Fire Princess",
            "color": "R",
            "rarity": "common",
            "type": "Creature \u2014 Human Noble",
            "number": 133,
            "color_identity": "R",
            "cost": "{1}{R}",
            "rules_text": "Whenever you discard a card, this creature deals 1 damage to each opponent.",
            "flavor_text": "[i][/i]",
            "pt": "2/2",
            "special_text": "",
            "shape": "normal",
            "set": "YGO",
            "loyalty": "",
            "artist": "ygoFire Princess",
            "notes": ""
        },
        {
            "card_name": "CR03 Raging Flame Sprite",
            "color": "R",
            "rarity": "common",
            "type": "Creature \u2014 Faerie",
            "number": 134,
            "color_identity": "R",
            "cost": "{1}{R}",
            "rules_text": "Whenever this creature attacks, it gets +2/+0 until end of turn.",
            "flavor_text": "[i][/i]",
            "pt": "1/2",
            "special_text": "",
            "shape": "normal",
            "set": "YGO",
            "loyalty": "",
            "artist": "ygoRaging Flame Sprite",
            "notes": ""
        },
        {
            "card_name": "CR04 Berserk Gorilla",
            "color": "R",
            "rarity": "common",
            "type": "Creature \u2014 Ape",
            "number": 135,
            "color_identity": "R",
            "cost": "{2}{R}",
            "rules_text": "When this creature enters, you may take a risk. If you do, this creature deals 2 damage to target creature or planeswalker. [i](To take a risk, discard a card, then look at the top card of your library. If it shares a card type with the discarded card, you may reveal it and put it into your hand.)[/i]",
            "flavor_text": "[i][/i]",
            "pt": "2/2",
            "special_text": "",
            "shape": "normal",
            "set": "YGO",
            "loyalty": "",
            "artist": "ygoBerserk Gorilla",
            "notes": ""
        },
        {
            "card_name": "CR05 Hitotsu-Me Giant",
            "color": "R",
            "rarity": "common",
            "type": "Creature \u2014 Cyclops",
            "number": 136,
            "color_identity": "R",
            "cost": "{2}{R}",
            "rules_text": "This creature can't attack or block alone.",
            "flavor_text": "[i][/i]",
            "pt": "4/4",
            "special_text": "",
            "shape": "normal",
            "set": "YGO",
            "loyalty": "",
            "artist": "ygoHitotsu-Me Giant",
            "notes": ""
        },
        {
            "card_name": "CR06 Flame Cerebrus",
            "color": "R",
            "rarity": "common",
            "type": "Creature \u2014 Dog",
            "number": 137,
            "color_identity": "R",
            "cost": "{3}{R}",
            "rules_text": "Tribute summon {3} [i](Each untapped creature with power 2 or more you sacrifice while casting this spell pays for {3}.)[/i]\nWhen this creature enters, if a creature was tributed, this creature deals 3 damage to you.",
            "flavor_text": "[i][/i]",
            "pt": "4/4",
            "special_text": "",
            "shape": "normal",
            "set": "YGO",
            "loyalty": "",
            "artist": "ygoFlame Cerebrus",
            "notes": ""
        },
        {
            "card_name": "CR07 Slot Machine",
            "color": "R",
            "rarity": "common",
            "type": "Artifact Creature \u2014 Construct",
            "number": 138,
            "color_identity": "R",
            "cost": "{4}{R}",
            "rules_text": "Whenever one or more creatures you control attacks, create a Treasure token. [i](It's an artifact with \u201c{T}, Sacrifice this artifact: Add one mana of any color.\u201d)[/i]",
            "flavor_text": "[i][/i]",
            "pt": "5/3",
            "special_text": "",
            "shape": "normal",
            "set": "YGO",
            "loyalty": "",
            "artist": "ygoSlot Machine",
            "notes": "!related Treasure"
        },
        {
            "card_name": "CR08 Flame Manipulator",
            "color": "R",
            "rarity": "common",
            "type": "Creature \u2014 Human Wizard",
            "number": 139,
            "color_identity": "R",
            "cost": "{3}{R}{R}",
            "rules_text": "Haste\nWhen this creature enters, target creature can't block this turn.",
            "flavor_text": "[i][/i]",
            "pt": "4/3",
            "special_text": "",
            "shape": "normal",
            "set": "YGO",
            "loyalty": "",
            "artist": "ygoFlame Manipulator",
            "notes": ""
        },
        {
            "card_name": "CR09 Mechanicalchaser",
            "color": "R",
            "rarity": "common",
            "type": "Artifact Creature \u2014 Construct",
            "number": 140,
            "color_identity": "R",
            "cost": "{4}{R}{R}",
            "rules_text": "Menace\nWhenever this creature enters or attacks, target attacking creature gains menace until end of turn.",
            "flavor_text": "[i][/i]",
            "pt": "5/4",
            "special_text": "",
            "shape": "normal",
            "set": "YGO",
            "loyalty": "",
            "artist": "ygoMechanicalchaser",
            "notes": ""
        },
        {
            "card_name": "CR10 Sparks",
            "color": "R",
            "rarity": "common",
            "type": "Instant",
            "number": 141,
            "color_identity": "R",
            "cost": "{R}",
            "rules_text": "As you cast this spell, you may take a risk. [i](Discard a card, then look at the top card of your library. If it shares a card type with the discarded card, you may reveal it and put it into your hand.)[/i]\nThis spell deals 2 damage to any target. If you took the risk, it deals 3 damage instead.",
            "flavor_text": "[i][/i]",
            "pt": "",
            "special_text": "",
            "shape": "normal",
            "set": "YGO",
            "loyalty": "",
            "artist": "ygoSparks",
            "notes": ""
        },
        {
            "card_name": "CR11 Raise Body Heat",
            "color": "R",
            "rarity": "common",
            "type": "Instant",
            "number": 142,
            "color_identity": "R",
            "cost": "{1}{R}",
            "rules_text": "Target creature gets +4/+1 until end of turn. Scry 1.",
            "flavor_text": "[i][/i]",
            "pt": "",
            "special_text": "",
            "shape": "normal",
            "set": "YGO",
            "loyalty": "",
            "artist": "ygoRaise Body Heat",
            "notes": ""
        },
        {
            "card_name": "CR12 Reload",
            "color": "R",
            "rarity": "common",
            "type": "Sorcery",
            "number": 143,
            "color_identity": "R",
            "cost": "{1}{R}",
            "rules_text": "You may discard a card or tap a legendary artifact you control. If you do, draw two cards.",
            "flavor_text": "[i][/i]",
            "pt": "",
            "special_text": "",
            "shape": "normal",
            "set": "YGO",
            "loyalty": "",
            "artist": "ygoReload",
            "notes": ""
        },
        {
            "card_name": "CR13 Stamping Destruction",
            "color": "R",
            "rarity": "common",
            "type": "Sorcery",
            "number": 144,
            "color_identity": "R",
            "cost": "{2}{R}",
            "rules_text": "Choose one\u2014\n\u2022 This spell deals 2 damage to target creature.\n\u2022 Destroy target artifact.\nForetell {R} [i](During your turn, you may pay {2} and exile this card from your hand face down. Cast it on a later turn for its foretell cost.)[/i]",
            "flavor_text": "[i][/i]",
            "pt": "",
            "special_text": "",
            "shape": "normal",
            "set": "YGO",
            "loyalty": "",
            "artist": "ygoStamping Destruction",
            "notes": ""
        },
        {
            "card_name": "CR15 Meteor of Destruction",
            "color": "R",
            "rarity": "common",
            "type": "Instant",
            "number": 146,
            "color_identity": "R",
            "cost": "{4}{R}",
            "rules_text": "As you cast this spell, you may take a risk. [i](Discard a card, then look at the top card of your library. If it shares a card type with the discarded card, you may reveal it and put it into your hand.)[/i]\nThis spell deals 5 damage to target creature, then if you took the risk, it also deals 2 damage to that creature's controller.",
            "flavor_text": "[i][/i]",
            "pt": "",
            "special_text": "",
            "shape": "normal",
            "set": "YGO",
            "loyalty": "",
            "artist": "ygoMeteor of Destruction",
            "notes": ""
        },
        {
            "card_name": "CR14 Rebellion",
            "color": "R",
            "rarity": "common",
            "type": "Sorcery",
            "number": 145,
            "color_identity": "R",
            "cost": "{3}{R}",
            "rules_text": "This spell costs {2} less to cast if you discarded a card this turn.\nGain control of target creature until end of turn. Untap that creature. It gains haste until end of turn.",
            "flavor_text": "[i][/i]",
            "pt": "",
            "special_text": "",
            "shape": "normal",
            "set": "YGO",
            "loyalty": "",
            "artist": "ygoRebellion",
            "notes": ""
        },
        {
            "card_name": "CG01 Leghul",
            "color": "G",
            "rarity": "common",
            "type": "Creature \u2014 Insect",
            "number": 170,
            "color_identity": "G",
            "cost": "{G}",
            "rules_text": "Deathtouch",
            "flavor_text": "[i][/i]",
            "pt": "1/1",
            "special_text": "",
            "shape": "normal",
            "set": "YGO",
            "loyalty": "",
            "artist": "ygoLeghul",
            "notes": ""
        },
        {
            "card_name": "CG02 Witch of the Black Forest",
            "color": "G",
            "rarity": "common",
            "type": "Creature \u2014 Elf Warlock",
            "number": 171,
            "color_identity": "G",
            "cost": "{1}{G}",
            "rules_text": "{T}: Add one mana of any color.",
            "flavor_text": "[i][/i]",
            "pt": "1/3",
            "special_text": "",
            "shape": "normal",
            "set": "YGO",
            "loyalty": "",
            "artist": "ygoWitch of the BLack Forest",
            "notes": ""
        },
        {
            "card_name": "CG03 Flower Wolf",
            "color": "G",
            "rarity": "common",
            "type": "Creature \u2014 Plant Dog",
            "number": 172,
            "color_identity": "G",
            "cost": "{1}{G}",
            "rules_text": "[i][i]Home Forest \u2014[/i][/i] As long as you control three or more Forests, this creature gets +1/+1 and has trample.",
            "flavor_text": "[i][/i]",
            "pt": "2/2",
            "special_text": "",
            "shape": "normal",
            "set": "YGO",
            "loyalty": "",
            "artist": "ygoFlower Wolf",
            "notes": ""
        },
        {
            "card_name": "CG04 Basic Insect",
            "color": "G",
            "rarity": "common",
            "type": "Creature \u2014 Insect",
            "number": 173,
            "color_identity": "G",
            "cost": "{2}{G}",
            "rules_text": "{1}, Sacrifice this creature: Destroy target artifact or enchantment.",
            "flavor_text": "[i][/i]",
            "pt": "2/2",
            "special_text": "",
            "shape": "normal",
            "set": "YGO",
            "loyalty": "",
            "artist": "ygoBasic Insect",
            "notes": ""
        },
        {
            "card_name": "CG05 Dark Gray",
            "color": "G",
            "rarity": "common",
            "type": "Creature \u2014 Beast",
            "number": 174,
            "color_identity": "G",
            "cost": "{2}{G}",
            "rules_text": "Vigilance",
            "flavor_text": "[i]Entirely gray, this beast has rarely been seen by mortal eyes.[/i]",
            "pt": "3/3",
            "special_text": "",
            "shape": "normal",
            "set": "YGO",
            "loyalty": "",
            "artist": "ygoDark Gray",
            "notes": ""
        },
        {
            "card_name": "CG06 Gazelle, King of Mythical Beasts",
            "color": "G",
            "rarity": "common",
            "type": "Legendary Creature \u2014 Beast",
            "number": 175,
            "color_identity": "G",
            "cost": "{2}{G}",
            "rules_text": "[i]Home Forest \u2014[/i] When this creature enters, if you control three or more Forests, you may have it fight target creature you don't control. [i](Each deals damage equal to its power to the other.)[/i]",
            "flavor_text": "[i][/i]",
            "pt": "3/3",
            "special_text": "",
            "shape": "normal",
            "set": "YGO",
            "loyalty": "",
            "artist": "ygoGazelle the King of Mythical Beasts",
            "notes": ""
        },
        {
            "card_name": "CG07 Mother Grizzly",
            "color": "G",
            "rarity": "common",
            "type": "Creature \u2014 Bear",
            "number": 176,
            "color_identity": "G",
            "cost": "{2}{G}{G}",
            "rules_text": "When this creature dies, create a 2/2 green Bear creature token.",
            "flavor_text": "[i][/i]",
            "pt": "3/3",
            "special_text": "",
            "shape": "normal",
            "set": "YGO",
            "loyalty": "",
            "artist": "ygoMother Grizzly",
            "notes": "!related Bear"
        },
        {
            "card_name": "CG09 Bazoo, the Soul-Eater",
            "color": "G",
            "rarity": "common",
            "type": "Legendary Creature \u2014 Ape",
            "number": 178,
            "color_identity": "G",
            "cost": "{4}{G}{G}",
            "rules_text": "Tribute summon {2} [i](Each untapped creature with power 2 or more you sacrifice while casting this spell pays for {2}.)[/i]\nWhen this creature enters, put a +1/+1 counter on it for each creature tributed.",
            "flavor_text": "[i][/i]",
            "pt": "4/3",
            "special_text": "",
            "shape": "normal",
            "set": "YGO",
            "loyalty": "",
            "artist": "ygoBazoo the Soul-Eater",
            "notes": ""
        },
        {
            "card_name": "CG08 Amazoness Chain Master",
            "color": "G",
            "rarity": "common",
            "type": "Creature \u2014 Human Warrior",
            "number": 177,
            "color_identity": "G",
            "cost": "{3}{G}{G}",
            "rules_text": "Reach\n{3}{G}, Sacrifice a creature: Destroy target creature with flying.",
            "flavor_text": "[i][/i]",
            "pt": "5/4",
            "special_text": "",
            "shape": "normal",
            "set": "YGO",
            "loyalty": "",
            "artist": "ygoAmazoness Chain Master",
            "notes": ""
        },
        {
            "card_name": "CG10 Megazowler",
            "color": "G",
            "rarity": "common",
            "type": "Creature \u2014 Dinosaur",
            "number": 179,
            "color_identity": "G",
            "cost": "{6}{G}{G}",
            "rules_text": "Tribute Summon {3} [i](Each untapped creature with power 2 or more you sacrifice while casting this spell pays for {3}.)[/i]\nForetell {3}{G}{G}{G} [i](During your turn, you may pay {2} and exile this card from your hand face down. Cast it on a later turn for its foretell cost.)[/i]",
            "flavor_text": "[i][/i]",
            "pt": "7/5",
            "special_text": "",
            "shape": "normal",
            "set": "YGO",
            "loyalty": "",
            "artist": "ygoMegazowler",
            "notes": ""
        },
        {
            "card_name": "CG11 Spring of Rebirth",
            "color": "G",
            "rarity": "common",
            "type": "Enchantment \u2014 Aura",
            "number": 180,
            "color_identity": "G",
            "cost": "{G}",
            "rules_text": "Enchant creature\nEnchanted creature gets +1/+1 and has trample.\nSacrifice this enchantment: Draw a card.",
            "flavor_text": "[i][/i]",
            "pt": "",
            "special_text": "",
            "shape": "normal",
            "set": "YGO",
            "loyalty": "",
            "artist": "ygoSpring of Rebirth",
            "notes": ""
        },
        {
            "card_name": "CG12 Quick Attack",
            "color": "G",
            "rarity": "common",
            "type": "Sorcery",
            "number": 181,
            "color_identity": "G",
            "cost": "{2}{G}",
            "rules_text": "Target creature you control deals damage equal to its power to target creature or planeswalker you don't control.\nForetell {G} [i](During your turn, you may pay {2} and exile this card from your hand face down. Cast it on a later turn for its foretell cost.)[/i]",
            "flavor_text": "[i][/i]",
            "pt": "",
            "special_text": "",
            "shape": "normal",
            "set": "YGO",
            "loyalty": "",
            "artist": "ygoaQuick Attack",
            "notes": ""
        },
        {
            "card_name": "CG13 Rush Recklessly",
            "color": "G",
            "rarity": "common",
            "type": "Instant",
            "number": 182,
            "color_identity": "G",
            "cost": "{1}{G}",
            "rules_text": "Target creature gets +3/+3 and gains trample until end of turn.",
            "flavor_text": "[i][/i]",
            "pt": "",
            "special_text": "",
            "shape": "normal",
            "set": "YGO",
            "loyalty": "",
            "artist": "ygoRush Recklessly",
            "notes": ""
        },
        {
            "card_name": "CG15 Rain of Mercy",
            "color": "G",
            "rarity": "common",
            "type": "Sorcery",
            "number": 184,
            "color_identity": "G",
            "cost": "{3}{G}",
            "rules_text": "Mill four cards, then you may return a creature or land card from your graveyard to the hand. [i](To mill four cards, put the top four cards of your library into your graveyard.)[/i]",
            "flavor_text": "[i][/i]",
            "pt": "",
            "special_text": "",
            "shape": "normal",
            "set": "YGO",
            "loyalty": "",
            "artist": "ygoRain of Mercy",
            "notes": ""
        },
        {
            "card_name": "CG14 Gaia Power",
            "color": "G",
            "rarity": "common",
            "type": "Sorcery",
            "number": 183,
            "color_identity": "G",
            "cost": "{2}{G}",
            "rules_text": "As you cast this spell, you may take a risk. [i](Discard a card, then look at the top card of your library. If it shares a card type with the discarded card, you may reveal it and put it into your hand.)[/i]\nSearch your library for a basic land card, and reveal it. If you took the risk, put it onto the battlefield tapped, otherwise add it to your hand.",
            "flavor_text": "[i][/i]",
            "pt": "",
            "special_text": "",
            "shape": "normal",
            "set": "YGO",
            "loyalty": "",
            "artist": "ygoGaia Power",
            "notes": ""
        },
        {
            "card_name": "CU05 Aqua Madoor",
            "color": "U",
            "rarity": "common",
            "type": "Creature \u2014 Elemental Wizard",
            "number": 60,
            "color_identity": "U",
            "cost": "{2}{U}",
            "rules_text": "Instant and sorcery spells you cast cost {1} less to cast.",
            "flavor_text": "[i][/i]",
            "pt": "2/2",
            "special_text": "",
            "shape": "normal",
            "set": "YGO",
            "loyalty": "",
            "artist": "ygoAqua Madoor",
            "notes": ""
        },
        {
            "card_name": "CA01 Disk Magician",
            "color": "",
            "rarity": "common",
            "type": "Artifact Creature \u2014 Construct",
            "number": 243,
            "color_identity": "C",
            "cost": "{2}",
            "rules_text": "When this creature enters, scry 1. [i](Look at the top card of your library. You may put that card on the bottom of your library.)[/i]",
            "flavor_text": "[i][/i]",
            "pt": "2/1",
            "special_text": "",
            "shape": "normal",
            "set": "YGO",
            "loyalty": "",
            "artist": "",
            "notes": ""
        },
        {
            "card_name": "CA02 Metal Dragon",
            "color": "",
            "rarity": "common",
            "type": "Artifact Creature \u2014 Dragon",
            "number": 244,
            "color_identity": "C",
            "cost": "{3}",
            "rules_text": "Flying\nWhen this creature dies, draw a card.",
            "flavor_text": "[i][/i]",
            "pt": "2/2",
            "special_text": "",
            "shape": "normal",
            "set": "YGO",
            "loyalty": "",
            "artist": "",
            "notes": ""
        },
        {
            "card_name": "CA03 Yaranzo",
            "color": "",
            "rarity": "common",
            "type": "Artifact Creature \u2014 Shapeshifter",
            "number": 245,
            "color_identity": "C",
            "cost": "{4}",
            "rules_text": "When this creature enters, create a Treasure token. [i](It's an artifact with \u201c{T}, Sacrifice this artifact: Add one mana of any color.\u201d)[/i]",
            "flavor_text": "[i][/i]",
            "pt": "3/2",
            "special_text": "",
            "shape": "normal",
            "set": "YGO",
            "loyalty": "",
            "artist": "",
            "notes": "!related Treasure"
        },
        {
            "card_name": "CA05 Pitch-Black Power Stone",
            "color": "",
            "rarity": "common",
            "type": "Artifact",
            "number": 247,
            "color_identity": "C",
            "cost": "{3}",
            "rules_text": "{T}: Add one mana of any color.\nForetell {1} [i](During your turn, you may pay {2} and exile this card from your hand face down. Cast it on a later turn for its foretell cost.)[/i]",
            "flavor_text": "[i][/i]",
            "pt": "",
            "special_text": "",
            "shape": "normal",
            "set": "YGO",
            "loyalty": "",
            "artist": "",
            "notes": ""
        },
        {
            "card_name": "CL01 Ocean City Field",
            "color": "",
            "rarity": "common",
            "type": "Land \u2014 Field",
            "number": 257,
            "color_identity": "WU",
            "cost": "",
            "rules_text": "This land enters tapped.\n{T}: Add {W} or {U}",
            "flavor_text": "[i][/i]",
            "pt": "",
            "special_text": "",
            "shape": "normal",
            "set": "YGO",
            "loyalty": "",
            "artist": "ygoA Legendary Ocean",
            "notes": "!tapped"
        },
        {
            "card_name": "CL02 Dark Storm Field",
            "color": "",
            "rarity": "common",
            "type": "Land \u2014 Field",
            "number": 258,
            "color_identity": "UB",
            "cost": "",
            "rules_text": "This land enters tapped.\n{T}: Add {U} or {B}.",
            "flavor_text": "[i][/i]",
            "pt": "",
            "special_text": "",
            "shape": "normal",
            "set": "YGO",
            "loyalty": "",
            "artist": "ygoMystic Plasma Zone",
            "notes": "!tapped"
        },
        {
            "card_name": "CL03 Volcanic Field",
            "color": "",
            "rarity": "common",
            "type": "Land \u2014 Field",
            "number": 259,
            "color_identity": "BR",
            "cost": "",
            "rules_text": "This land enters tapped.\n{T}: Add {B} or {R}.",
            "flavor_text": "[i][/i]",
            "pt": "",
            "special_text": "",
            "shape": "normal",
            "set": "YGO",
            "loyalty": "",
            "artist": "ygoMolten Destruction",
            "notes": "!tapped"
        },
        {
            "card_name": "CL06 Temple Field",
            "color": "",
            "rarity": "common",
            "type": "Land \u2014 Field",
            "number": 262,
            "color_identity": "WB",
            "cost": "",
            "rules_text": "This land enters tapped.\n{T}: Add {W} or {B}.",
            "flavor_text": "[i][/i]",
            "pt": "",
            "special_text": "",
            "shape": "normal",
            "set": "YGO",
            "loyalty": "",
            "artist": "ygoMausoleum of the Emperor",
            "notes": "!tapped"
        },
        {
            "card_name": "CL04 Jurassic Field",
            "color": "",
            "rarity": "common",
            "type": "Land \u2014 Field",
            "number": 260,
            "color_identity": "RG",
            "cost": "",
            "rules_text": "This land enters tapped.\n{T}: Add {R} or {G}.",
            "flavor_text": "[i][/i]",
            "pt": "",
            "special_text": "",
            "shape": "normal",
            "set": "YGO",
            "loyalty": "",
            "artist": "ygoJurassic World",
            "notes": "!tapped"
        },
        {
            "card_name": "CL07 Virtual Field",
            "color": "",
            "rarity": "common",
            "type": "Land \u2014 Field",
            "number": 263,
            "color_identity": "UR",
            "cost": "",
            "rules_text": "This land enters tapped.\n{T}: Add {U} or {R}.",
            "flavor_text": "[i][/i]",
            "pt": "",
            "special_text": "",
            "shape": "normal",
            "set": "YGO",
            "loyalty": "",
            "artist": "ygoPseudo Space",
            "notes": "!tapped"
        },
        {
            "card_name": "CL05 Secret Village Field",
            "color": "",
            "rarity": "common",
            "type": "Land \u2014 Field",
            "number": 261,
            "color_identity": "WG",
            "cost": "",
            "rules_text": "This land enters tapped.\n{T}: Add {G} or {W}.",
            "flavor_text": "[i][/i]",
            "pt": "",
            "special_text": "",
            "shape": "normal",
            "set": "YGO",
            "loyalty": "",
            "artist": "ygoSecret Village of the Spellcasters",
            "notes": "!tapped"
        },
        {
            "card_name": "CL08 Graveyard Field",
            "color": "",
            "rarity": "common",
            "type": "Land \u2014 Field",
            "number": 264,
            "color_identity": "BG",
            "cost": "",
            "rules_text": "This land enters tapped.\n{T}: Add {B} or {G}.",
            "flavor_text": "[i][/i]",
            "pt": "",
            "special_text": "",
            "shape": "normal",
            "set": "YGO",
            "loyalty": "",
            "artist": "ygoCall of the Haunted",
            "notes": "!tapped"
        },
        {
            "card_name": "CL09 Ravine Field",
            "color": "",
            "rarity": "common",
            "type": "Land \u2014 Field",
            "number": 265,
            "color_identity": "WR",
            "cost": "",
            "rules_text": "This land enters tapped.\n{T}: Add {R} or {W}.",
            "flavor_text": "[i][/i]",
            "pt": "",
            "special_text": "",
            "shape": "normal",
            "set": "YGO",
            "loyalty": "",
            "artist": "ygoDragon Ravine",
            "notes": "!tapped"
        },
        {
            "card_name": "CL10 Wetland Field",
            "color": "",
            "rarity": "common",
            "type": "Land \u2014 Field",
            "number": 266,
            "color_identity": "UG",
            "cost": "",
            "rules_text": "This land enters tapped.\n{T}: Add {G} or {U}.",
            "flavor_text": "[i][/i]",
            "pt": "",
            "special_text": "",
            "shape": "normal",
            "set": "YGO",
            "loyalty": "",
            "artist": "ygoWetlands",
            "notes": "!tapped"
        },
        {
            "card_name": "CA06 Millennium Key",
            "color": "",
            "rarity": "common",
            "type": "Legendary Artifact",
            "number": 248,
            "color_identity": "C",
            "cost": "{2}",
            "rules_text": "This artifact enters tapped.\n{T}, Return this artifact to its owner's hand: Look at target opponent's hand.\n{2}, {T}: Exile target card from a graveyard.",
            "flavor_text": "[i][/i]",
            "pt": "",
            "special_text": "",
            "shape": "normal",
            "set": "YGO",
            "loyalty": "",
            "artist": "",
            "notes": "!tapped"
        },
        {
            "card_name": "CW01 Harpie Girl",
            "color": "W",
            "rarity": "common",
            "type": "Creature \u2014 Bird",
            "number": 18,
            "color_identity": "W",
            "cost": "{W}",
            "rules_text": "Flying\n{3}{W}, {T}: Tap target creature.",
            "flavor_text": "[i][/i]",
            "pt": "1/1",
            "special_text": "",
            "shape": "normal",
            "set": "YGO",
            "loyalty": "",
            "artist": "ygoHarpie Girl",
            "notes": ""
        },
        {
            "card_name": "CU06 Flying Fish",
            "color": "U",
            "rarity": "common",
            "type": "Creature \u2014 Fish",
            "number": 61,
            "color_identity": "U",
            "cost": "{3}{U}",
            "rules_text": "Flash [i](You may cast this spell any time you could cast an instant.)[/i]\nFlying",
            "flavor_text": "[i][/i]",
            "pt": "2/2",
            "special_text": "",
            "shape": "normal",
            "set": "YGO",
            "loyalty": "",
            "artist": "ygoFlying Fish",
            "notes": ""
        },
        {
            "card_name": "CA04 Millennium Scale",
            "color": "",
            "rarity": "common",
            "type": "Legendary Artifact",
            "number": 246,
            "color_identity": "C",
            "cost": "{2}",
            "rules_text": "{2}, {T}: Put a finality counter on target creature. [i](If a creature with a finality counter on it would die, exile it instead.)[/i]",
            "flavor_text": "[i][/i]",
            "pt": "",
            "special_text": "",
            "shape": "normal",
            "set": "YGO",
            "loyalty": "",
            "artist": "",
            "notes": ""
        },
        {
            "card_name": "CW02 Marauding Captain",
            "color": "W",
            "rarity": "common",
            "type": "Creature \u2014 Soldier",
            "number": 19,
            "color_identity": "W",
            "cost": "{1}{W}",
            "rules_text": "{2}{W}{W}: Creatures you control get +1/+1 until end of turn. Activate only as a sorcery.",
            "flavor_text": "[i][/i]",
            "pt": "2/2",
            "special_text": "",
            "shape": "normal",
            "set": "YGO",
            "loyalty": "",
            "artist": "ygoMarauding Captain",
            "notes": ""
        },
        {
            "card_name": "CU07 Humanoid Worm Drake",
            "color": "U",
            "rarity": "common",
            "type": "Creature \u2014 Drake",
            "number": 62,
            "color_identity": "U",
            "cost": "{3}{U}{U}",
            "rules_text": "Tribute Summon {3} [i](Each untapped creature with power 2 or more you sacrifice while casting this spell pays for {3}.)[/i]\nFlying",
            "flavor_text": "[i][/i]",
            "pt": "4/3",
            "special_text": "",
            "shape": "normal",
            "set": "YGO",
            "loyalty": "",
            "artist": "ygoHumanoid Worm Drake",
            "notes": ""
        },
        {
            "card_name": "Goat",
            "color": "W",
            "rarity": "common",
            "type": "Token Creature \u2014 Goat",
            "number": 1,
            "color_identity": "W",
            "cost": "",
            "rules_text": "",
            "flavor_text": "[i][/i]",
            "pt": "1/1",
            "special_text": "",
            "shape": "token",
            "set": "YGO",
            "loyalty": "",
            "artist": "ygoGoat Token (blue)",
            "notes": ""
        },
        {
            "card_name": "Soldier",
            "color": "W",
            "rarity": "common",
            "type": "Token Creature \u2014 Soldier",
            "number": 2,
            "color_identity": "W",
            "cost": "",
            "rules_text": "This creature can't block.",
            "flavor_text": "[i][/i]",
            "pt": "2/1",
            "special_text": "",
            "shape": "token",
            "set": "YGO",
            "loyalty": "",
            "artist": "ygoFamiliar Knight",
            "notes": ""
        },
        {
            "card_name": "Bear",
            "color": "G",
            "rarity": "common",
            "type": "Token Creature \u2014 Bear",
            "number": 4,
            "color_identity": "G",
            "cost": "",
            "rules_text": "",
            "flavor_text": "[i][/i]",
            "pt": "2/2",
            "special_text": "",
            "shape": "token",
            "set": "YGO",
            "loyalty": "",
            "artist": "ygoMother Grizzly",
            "notes": ""
        },
        {
            "card_name": "Spirit",
            "color": "B",
            "rarity": "common",
            "type": "Token Creature \u2014 Spirit",
            "number": 3,
            "color_identity": "B",
            "cost": "",
            "rules_text": "",
            "flavor_text": "[i][/i]",
            "pt": "1/1",
            "special_text": "",
            "shape": "token",
            "set": "YGO",
            "loyalty": "",
            "artist": "ygoDouble Coston",
            "notes": ""
        },
        {
            "card_name": "Treasure",
            "color": "",
            "rarity": "common",
            "type": "Token Artifact \u2014 Treasure",
            "number": 5,
            "color_identity": "C",
            "cost": "",
            "rules_text": "{T}, Sacrifice this artifact: Add one mana of any color.",
            "flavor_text": "[i][/i]",
            "pt": "",
            "special_text": "",
            "shape": "token",
            "set": "YGO",
            "loyalty": "",
            "artist": "ygoGlory of the King's Hand",
            "notes": ""
        },
        {
            "card_name": "Plains",
            "color": "",
            "rarity": "common",
            "type": "Basic Land \u2014 Plains",
            "number": 277,
            "color_identity": "W",
            "cost": "",
            "rules_text": "",
            "flavor_text": "[i][/i]",
            "pt": "",
            "special_text": "",
            "shape": "normal",
            "set": "YGO",
            "loyalty": "",
            "artist": "",
            "notes": ""
        },
        {
            "card_name": "Forest",
            "color": "",
            "rarity": "common",
            "type": "Basic Land \u2014 Forest",
            "number": 285,
            "color_identity": "G",
            "cost": "",
            "rules_text": "",
            "flavor_text": "[i][/i]",
            "pt": "",
            "special_text": "",
            "shape": "normal",
            "set": "YGO",
            "loyalty": "",
            "artist": "",
            "notes": ""
        },
        {
            "card_name": "Mountain",
            "color": "",
            "rarity": "common",
            "type": "Basic Land \u2014 Mountain",
            "number": 283,
            "color_identity": "R",
            "cost": "",
            "rules_text": "",
            "flavor_text": "[i][/i]",
            "pt": "",
            "special_text": "",
            "shape": "normal",
            "set": "YGO",
            "loyalty": "",
            "artist": "",
            "notes": ""
        },
        {
            "card_name": "Swamp",
            "color": "",
            "rarity": "common",
            "type": "Basic Land \u2014 Swamp",
            "number": 282,
            "color_identity": "B",
            "cost": "",
            "rules_text": "",
            "flavor_text": "[i][/i]",
            "pt": "",
            "special_text": "",
            "shape": "normal",
            "set": "YGO",
            "loyalty": "",
            "artist": "",
            "notes": ""
        },
        {
            "card_name": "Island",
            "color": "",
            "rarity": "common",
            "type": "Basic Land \u2014 Island",
            "number": 279,
            "color_identity": "U",
            "cost": "",
            "rules_text": "",
            "flavor_text": "[i][/i]",
            "pt": "",
            "special_text": "",
            "shape": "normal",
            "set": "YGO",
            "loyalty": "",
            "artist": "",
            "notes": ""
        }
    ],
    "version": 1
}